<?xml version="1.0" encoding="UTF-8"?>
<includes>
	<include name="DialogButtonInfo">
		<width>204.7</width>
		<height>80</height>
		<align>center</align>
		<font>Font28_Reg</font>
		<textoffsetx>20</textoffsetx>
		<textcolor>$VAR[PanelSubTextColorVar]</textcolor>
		<focusedcolor>$VAR[PanelFocusTextColorVar]</focusedcolor>
		<disabledcolor>$VAR[PanelDisabledTextColorVar]</disabledcolor>
		<texturefocus colordiffuse="$VAR[PanelHighlightColorVar]" border="20">buttons/button.png</texturefocus>
		<texturenofocus colordiffuse="$VAR[PanelSubTextColorVar]" border="20">buttons/button.png</texturenofocus>
	</include>
	<include name="DialogButtonInfoIcon">
		<width>80</width>
		<height>80</height>
		<align>center</align>
		<font>Font40_Icon</font>
		<textcolor>$VAR[PanelSubTextColorVar]</textcolor>
		<focusedcolor>$VAR[PanelFocusTextColorVar]</focusedcolor>
		<disabledcolor>$VAR[PanelDisabledTextColorVar]</disabledcolor>
		<texturefocus colordiffuse="$VAR[PanelHighlightColorVar]" border="20">buttons/button.png</texturefocus>
		<texturenofocus colordiffuse="$VAR[PanelSubTextColorVar]" border="20">buttons/button.png</texturenofocus>
	</include>
	<include name="DialogInfoMovieButtons">
		
		<control type="button" id="103">
			<onclick>RunScript(script.embuary.helper,action=playcinema,type=movie,dbid=$INFO[ListItem.DBID])</onclick>
			<label>Cinema</label>
			<include>DialogButtonInfo</include>
		</control>
		<control type="button" id="111">
			<label>Cast</label>
			<include>DialogButtonInfo</include>
		</control>
		<control type="button" id="112">
			<visible>System.HasAddon(script.extendedinfo)</visible>
			<label>Cast</label>
			<include>DialogButtonInfo</include>
		</control>
		<control type="button" id="113">
			<!-- <visible>!String.IsEmpty(ListItem.SetID)</visible> -->
			<label>Crew</label>
			<include>DialogButtonInfo</include>
		</control>
		<control type="button" id="114">
			<!-- <visible>!String.IsEmpty(ListItem.SetID)</visible> -->
			<label>Set</label>
			<include>DialogButtonInfo</include>
		</control>
		<control type="button" id="115">
			<!-- <visible>!String.IsEmpty(ListItem.SetID)</visible> -->
			<label>Director</label>
			<include>DialogButtonInfo</include>
		</control>
		<control type="button" id="116">
			<!-- <visible>!String.IsEmpty(ListItem.SetID)</visible> -->
			<label>Writer</label>
			<include>DialogButtonInfo</include>
		</control>
		<control type="button" id="117">
			<!-- <visible>!String.IsEmpty(ListItem.SetID)</visible> -->
			<label>Similar</label>
			<include>DialogButtonInfo</include>
		</control>
		<control type="button" id="119">
			<!-- <visible>!String.IsEmpty(ListItem.SetID)</visible> -->
			<label>Studio</label>
			<include>DialogButtonInfo</include>
		</control>
		<control type="button" id="120">
			<!-- <visible>!String.IsEmpty(ListItem.SetID)</visible> -->
			<label>Genre</label>
			<include>DialogButtonInfo</include>
		</control>
		<control type="button" id="121">
			<visible>System.HasAddon(plugin.video.youtube)</visible>
			<label>Youtube</label>
			<include>DialogButtonInfo</include>
		</control>
	</include>
	<include name="DialogInfoActors">
		<control type="group" id="9001">
			<!-- Set -->
			<include content="DialogInfoExtenedInfo">
				<param name="id">111</param>
				<param name="content">videodb://movies/sets/$INFO[ListItem.SetID]</param>
			</include>
			<!-- Youtube -->
			<include content="DialogInfoExtenedInfoYoutube">
				<param name="id">112</param>
				<param name="content">plugin://script.extendedinfo?info=youtubesearchvideos&amp;&amp;id=$ESCINFO[ListItem.Title] $LOCALIZE[20410]</param>
			</include>
			<!-- Similar -->
			<include content="DialogInfoExtenedInfo">
				<param name="id">113</param>
				<param name="content">plugin://script.extendedinfo?info=similarmovies&amp;&amp;dbid=$INFO[ListItem.DBID]</param>
			</include>
		</control>
	</include>
	<include name="DialogInfoMovies">
		<control type="group" id="9001">
			<!-- Set -->
			<include content="DialogInfoExtenedInfo">
				<param name="id">111</param>
				<param name="content">videodb://movies/sets/$INFO[ListItem.SetID]</param>
			</include>
			<!-- Youtube -->
			<include content="DialogInfoExtenedInfoYoutube">
				<param name="id">112</param>
				<param name="content">plugin://script.extendedinfo?info=youtubesearchvideos&amp;&amp;id=$ESCINFO[ListItem.Title] $LOCALIZE[20410]</param>
			</include>
			<!-- Similar -->
			<include content="DialogInfoExtenedInfo">
				<param name="id">113</param>
				<param name="content">plugin://script.extendedinfo?info=similarmovies&amp;&amp;dbid=$INFO[ListItem.DBID]</param>
			</include>
		</control>
	</include>
	<include name="DialogInfoTVShowButtons">
		<control type="button" id="111">
			<visible>String.IsEqual(ListItem.DBTYPE,tvshow)</visible>
			<label>$LOCALIZE[33054]</label>
			<include>DialogButtonInfo</include>
		</control>
		<control type="button" id="112">
			<visible>System.HasAddon(script.extendedinfo)</visible>
			<label>YouTube</label>
			<include>DialogButtonInfo</include>
		</control>
		<control type="button" id="113">
			<visible>System.HasAddon(script.extendedinfo) + !String.IsEqual(ListItem.DBTYPE,episode)</visible>
			<label>$LOCALIZE[31110]</label>
			<include>DialogButtonInfo</include>
		</control>
	</include>
	<include name="DialogInfoTVShows">
		<control type="group" id="9001">
			<!-- Seasons -->
			<include content="DialogInfoExtenedInfo">
				<param name="id">111</param>
				<param name="content">videodb://tvshows/titles/$INFO[ListItem.DBID]/</param>
				<param name="visible">String.IsEqual(ListItem.DBTYPE,tvshow)</param>
			</include>
			<!-- Youtube -->
			<include content="DialogInfoExtenedInfoYoutube">
				<param name="id">112</param>
				<param name="content">$VAR[VideoInfoTVShowYoutubePath]</param>
			</include>
			<!-- Similar -->
			<include content="DialogInfoExtenedInfo">
				<param name="id">113</param>
				<param name="content">plugin://script.extendedinfo?info=similartvshows&amp;&amp;dbid=$INFO[ListItem.DBID]</param>
				<param name="visible">!String.IsEqual(ListItem.DBTYPE,episode)</param>
			</include>
		</control>
	</include>
	<include name="DialogInfoMusicButtons">
		<control type="button" id="114">
			<visible>String.IsEqual(ListItem.DBTYPE,artist)</visible>
			<label>Albums</label>
			<include>DialogButtonInfo</include>
		</control>
		<control type="button" id="115">
			<visible>String.IsEqual(ListItem.DBTYPE,artist)</visible>
			<label>$LOCALIZE[21888]</label>
			<include>DialogButtonInfo</include>
		</control>
		<control type="button" id="111">
			<visible>Container.Content(musicvideos) + System.HasAddon(script.extendedinfo)</visible>
			<label>$LOCALIZE[21888]</label>
			<include>DialogButtonInfo</include>
		</control>
		<control type="button" id="112">
			<visible>System.HasAddon(script.extendedinfo)</visible>
			<label>YouTube</label>
			<include>DialogButtonInfo</include>
		</control>
		<control type="button" id="113">
			<visible>Container.Content(musicvideos) + System.HasAddon(script.extendedinfo)</visible>
			<label>Top tracks</label>
			<include>DialogButtonInfo</include>
		</control>
		<control type="button" id="116">
			<visible>Container.Content(artists) + System.HasAddon(script.skin.helper.service)</visible>
			<label>$LOCALIZE[31110]</label>
			<include>DialogButtonInfo</include>
		</control>
		<control type="button" id="117">
			<visible>Container.Content(albums)</visible>
			<label>Arist Info</label>
			<include>DialogButtonInfo</include>
		</control>
	</include>
	<include name="DialogInfoMusic">
		<control type="group" id="9001">
			<!-- Albums -->
			<include content="DialogInfoExtenedInfoMusic">
				<param name="id">114</param>
				<param name="content">musicdb://artists/$INFO[ListItem.DBID]</param>
			</include>
			<!-- Discography -->
			<include content="DialogInfoExtenedInfoMusic">
				<param name="id">111</param>
				<param name="content">plugin://script.extendedinfo?info=discography&amp;&amp;artistname=$INFO[ListItem.Artist]</param>
			</include>
			<!-- Youtube -->
			<include content="DialogInfoExtenedInfoYoutube">
				<param name="id">112</param>
				<param name="content">$VAR[MusicDialogYoutubeVar]</param>
			</include>
			<!-- Most loved tracks -->
			<include content="DialogInfoExtenedInfoYoutube">
				<param name="id">113</param>
				<param name="content">plugin://script.extendedinfo?info=mostlovedtracks&amp;&amp;artistname=$INFO[ListItem.Artist]</param>
			</include>
		</control>
	</include>
	<include name="DialogExtraInfo">
		<param name="id"></param>
		<param name="buttonid"></param>
		<param name="label">false</param>
		<definition>
			<visible>Control.IsVisible($PARAM[buttonid])</visible>
			<animation type="Conditional" condition="Control.HasFocus($PARAM[id]) | Control.HasFocus($PARAM[buttonid])]">
				<effect type="fade" start="0" end="100" time="200" />
				<effect type="slide" start="1920" end="0" time="0" />
			</animation>
			<animation type="Conditional" condition="![Control.HasFocus($PARAM[id]) | Control.HasFocus($PARAM[buttonid])]">
				<effect type="fade" start="100" end="0" time="200" />
				<effect type="slide" start="0" end="1920" time="0" delay="200"/>
			</animation>
			<left>-10</left>
			<top>163</top>
			<height>400</height>
			<width>1179</width>
			<include>AnimationVisibleFade</include>
			<orientation>horizontal</orientation>
			<itemlayout height="344" width="235.8">
				<include content="ViewArtwork">
					<param name="diffuse">diffuse/rounded5-247x370.png</param>
				</include>
				<control type="image">
					<visible>$PARAM[label]</visible>
					<left>10</left>
					<right>10</right>
					<bottom>10</bottom>
					<height>90</height>
					<texture border="5">panels/art-overlay.png</texture>
				</control>
				<control type="label">
					<visible>$PARAM[label]</visible>
					<left>15</left>
					<right>15</right>
					<bottom>15</bottom>
					<height>60</height>
					<font>Font25_Cond</font>
					<label>$INFO[ListItem.Label][CR][COLOR $VAR[PanelSubTextColorVar]]$INFO[ListItem.Label2][/COLOR]</label>
					<textcolor>$VAR[PanelTextColorVar]</textcolor>
				</control>
				<!-- <control type="label">
					<left>15</left>
					<right>15</right>
					<bottom>15</bottom>
					<height>30</height>
					<font>Font25_Cond</font>
					<label>$INFO[ListItem.Label2]</label>
					<textcolor>$VAR[PanelSubTextColorVar]</textcolor>
				</control> -->
			</itemlayout>
			<focusedlayout height="344" width="235.8">
				<control type="image">
					
					<texture border="10" colordiffuse="$VAR[PanelHighlightColorVar]">buttons/panel-select-focus.png</texture>
				</control>
				<include content="ViewArtwork">
					<param name="diffuse">diffuse/rounded5-247x370.png</param>
				</include>
				<control type="image">
					<visible>$PARAM[label]</visible>
					<left>10</left>
					<right>10</right>
					<bottom>10</bottom>
					<height>90</height>
					<texture border="5">panels/art-overlay.png</texture>
				</control>
				<control type="label">
					<visible>$PARAM[label]</visible>
					<left>15</left>
					<right>15</right>
					<bottom>15</bottom>
					<height>60</height>
					<font>Font25_Cond</font>
					<label>$INFO[ListItem.Label][CR][COLOR $VAR[PanelTextColorVar]]$INFO[ListItem.Label2][/COLOR]</label>
					<textcolor>$VAR[PanelHighlightColorVar]</textcolor>
				</control>
			</focusedlayout>
		</definition>
	</include>
	<include name="DialogExtraInfoYoutube">
		<param name="id"></param>
		<param name="buttonid"></param>
		<param name="label">false</param>
		<definition>
			<visible>Control.IsVisible($PARAM[buttonid])</visible>
			<animation type="Conditional" condition="Control.HasFocus($PARAM[id]) | Control.HasFocus($PARAM[buttonid])]">
				<effect type="fade" start="0" end="100" time="200" />
				<effect type="slide" start="1920" end="0" time="0" />
			</animation>
			<animation type="Conditional" condition="![Control.HasFocus($PARAM[id]) | Control.HasFocus($PARAM[buttonid])]">
				<effect type="fade" start="100" end="0" time="200" />
				<effect type="slide" start="0" end="1920" time="0" delay="200"/>
			</animation>
			<left>-10</left>
			<top>163</top>
			<height>400</height>
			<width>1179</width>
			<include>AnimationVisibleFade</include>
			<orientation>horizontal</orientation>
			<itemlayout height="344" width="393">
				<include content="ViewArtwork">
					<param name="diffuse">diffuse/rounded5-247x370.png</param>
				</include>
				<control type="image">
					<visible>$PARAM[label]</visible>
					<left>10</left>
					<right>10</right>
					<bottom>10</bottom>
					<height>90</height>
					<texture border="5">panels/art-overlay.png</texture>
				</control>
				<control type="label">
					<visible>$PARAM[label]</visible>
					<left>15</left>
					<right>15</right>
					<bottom>15</bottom>
					<height>60</height>
					<font>Font25_Cond</font>
					<label>$INFO[ListItem.Label][CR][COLOR $VAR[PanelSubTextColorVar]]$INFO[ListItem.Label2][/COLOR]</label>
					<textcolor>$VAR[PanelTextColorVar]</textcolor>
				</control>
			</itemlayout>
			<focusedlayout height="344" width="393">
				<control type="image">
					
					<texture border="10" colordiffuse="$VAR[PanelHighlightColorVar]">buttons/panel-select-focus.png</texture>
				</control>
				<include content="ViewArtwork">
					<param name="diffuse">diffuse/rounded5-247x370.png</param>
				</include>
				<control type="image">
					<visible>$PARAM[label]</visible>
					<left>10</left>
					<right>10</right>
					<bottom>10</bottom>
					<height>90</height>
					<texture border="5">panels/art-overlay.png</texture>
				</control>
				<control type="label">
					<visible>$PARAM[label]</visible>
					<left>15</left>
					<right>15</right>
					<bottom>15</bottom>
					<height>60</height>
					<font>Font25_Cond</font>
					<label>$INFO[ListItem.Label][CR][COLOR $VAR[PanelTextColorVar]]$INFO[ListItem.Label2][/COLOR]</label>
					<textcolor>$VAR[PanelHighlightColorVar]</textcolor>
				</control>
			</focusedlayout>
		</definition>
	</include>
	<include name="DialogInfoActor">
		<param name="visible"></param>
		<definition>
			<control type="panel" id="50">
				<!-- <visible>$PARAM[visible]</visible> -->
				<include>AnimationVisibleFade</include>
				<orientation>horizontal</orientation>
				<onup condition="System.HasAddon(script.extendedinfo)">RunScript(script.embuary.info,call=person,query=$INFO[Container(50).ListItem.Label])</onup>
				<ondown condition="Control.IsVisible(130)">130</ondown>
				<ondown condition="!Control.IsVisible(130) + Control.IsVisible(131)">131</ondown>
				<ondown condition="!Control.IsVisible(130) + !Control.IsVisible(131)">9000</ondown>
				<itemlayout height="224" width="234">
					<control type="image">
						<width>224</width>
						<texture border="10" colordiffuse="$VAR[PanelSubTextColorVar]">buttons/panel-select-focus.png</texture>
					</control>
					<control type="image">
						<top>10</top>
						<left>10</left>
						<width>204</width>
						<height>204</height>
						<aspectratio>scale</aspectratio>
						<texture>$INFO[ListItem.Thumb]</texture>
					</control>
					<control type="image">
						<left>10</left>
						<top>184</top>
						<width>204</width>
						<height>30</height>
						<texture>colors/black50.png</texture>
					</control>
					<control type="label">
						<left>15</left>
						<top>184</top>
						<width>194</width>
						<height>30</height>
						<align>center</align>
						<font>Font25_Cond</font>
						<label>$INFO[ListItem.Label]</label>
						<textcolor>$VAR[PanelTextColorVar]</textcolor>
					</control>
				</itemlayout>
				<focusedlayout height="224" width="234">
					<control type="image">
						<width>224</width>
						<texture border="10" colordiffuse="$VAR[PanelHighlightColorVar]">buttons/panel-select-focus.png</texture>
					</control>
					<control type="image">
						<top>10</top>
						<left>10</left>
						<width>204</width>
						<height>204</height>
						<aspectratio>scale</aspectratio>
						<texture>$INFO[ListItem.Thumb]</texture>
					</control>
					<control type="image">
						<left>10</left>
						<top>184</top>
						<width>204</width>
						<height>30</height>
						<texture>colors/black50.png</texture>
					</control>
					<control type="label">
						<left>15</left>
						<top>184</top>
						<width>194</width>
						<height>30</height>
						<align>center</align>
						<font>Font25_Cond</font>
						<label>$INFO[ListItem.Label]</label>
						<textcolor>$VAR[PanelFocusTextColorVar]</textcolor>
					</control>
				</focusedlayout>
			</control>
		</definition>
	</include>
	<include name="DialogInfoActorMusic">
		<param name="visible"></param>
		<definition>
			<control type="panel" id="50">
				<!-- <visible>$PARAM[visible]</visible> -->
				<include>AnimationVisibleFade</include>
				<orientation>horizontal</orientation>
				<onup condition="System.HasAddon(script.extendedinfo)">RunScript(script.extendedinfo,info=extendedactorinfo,name=$INFO[Container(50).ListItem.Label])</onup>
				<ondown condition="Control.IsVisible(130)">130</ondown>
				<ondown condition="!Control.IsVisible(130) + Control.IsVisible(131)">131</ondown>
				<ondown condition="!Control.IsVisible(130) + !Control.IsVisible(131)">9000</ondown>
				<top>201</top>
				<right>25</right>
				<height>348</height>
				<ondown>9000</ondown>
				<pagecontrol>60</pagecontrol>
				
				<itemlayout height="49">
					<control type="label">
						<width>180</width>
						<font>Font28_Reg</font>
						<label>$INFO[ListItem.Label2]</label>
						<textcolor>$VAR[PanelTextColorVar]</textcolor>
					</control>
					<control type="image">
						<top>1</top>
						<left>180</left>
						<width>4</width>
						<height>48</height>
						<texture colordiffuse="$VAR[PanelListSeparatorColorVar]">panels/line-vertical.png</texture>
					</control>
					<control type="label">
						<left>200</left>
						<font>Font28_Reg</font>
						<label>$INFO[ListItem.Label]</label>
						<textcolor>$VAR[PanelSubTextColorVar]</textcolor>
					</control>
					<control type="image">
						<top>49</top>
						<height>4</height>
						<texture border="0,0,220,0" colordiffuse="$VAR[PanelListSeparatorColorVar]">panels/separator.png</texture>
					</control>
				</itemlayout>
				<focusedlayout height="49">
					<control type="image">
						<top>1</top>
						<left>181</left>
						<height>48</height>
						<texture border="10" colordiffuse="$VAR[PanelHighlightColorVar]">buttons/list-select-focus.png</texture>
					</control>
					<control type="label">
						<width>180</width>
						<font>Font28_Reg</font>
						<label>$INFO[ListItem.Label2]</label>
						<textcolor>$VAR[PanelTextColorVar]</textcolor>
					</control>
					<control type="image">
						<top>1</top>
						<left>180</left>
						<width>4</width>
						<height>48</height>
						<texture colordiffuse="$VAR[PanelListSeparatorColorVar]">panels/line-vertical.png</texture>
					</control>
					<control type="label">
						<left>200</left>
						<font>Font28_Reg</font>
						<label>$INFO[ListItem.Label]</label>
						<textcolor>$VAR[PanelFocusTextColorVar]</textcolor>
					</control>
					<control type="image">
						<top>49</top>
						<height>4</height>
						<texture border="0,0,220,0" colordiffuse="$VAR[PanelListSeparatorColorVar]">panels/separator.png</texture>
					</control>
				</focusedlayout>
			</control>
		</definition>
	</include>
	<include name="DialogInfoTracksMusic">
		<param name="visible"></param>
		<definition>
			<control type="panel" id="50">
				<!-- <visible>$PARAM[visible]</visible> -->
				<include>AnimationVisibleFade</include>
				<orientation>horizontal</orientation>
				<onup condition="System.HasAddon(script.extendedinfo)">RunScript(script.extendedinfo,info=extendedactorinfo,name=$INFO[Container(50).ListItem.Label])</onup>
				<ondown condition="Control.IsVisible(130)">130</ondown>
				<ondown condition="!Control.IsVisible(130) + Control.IsVisible(131)">131</ondown>
				<ondown condition="!Control.IsVisible(130) + !Control.IsVisible(131)">9000</ondown>
				<top>201</top>
				<right>25</right>
				<height>348</height>
				<ondown>9000</ondown>
				<pagecontrol>60</pagecontrol>
				
				<itemlayout height="49">
					<control type="label">
						<width>55</width>
						<font>Font28_Reg</font>
						<label>$INFO[ListItem.TrackNumber]</label>
						<textcolor>$VAR[PanelTextColorVar]</textcolor>
					</control>
					<control type="image">
						<top>1</top>
						<left>55</left>
						<width>4</width>
						<height>48</height>
						<texture colordiffuse="$VAR[PanelListSeparatorColorVar]">panels/line-vertical.png</texture>
					</control>
					<control type="label">
						<left>75</left>
						<font>Font28_Reg</font>
						<label>$INFO[ListItem.Label]</label>
						<textcolor>$VAR[PanelSubTextColorVar]</textcolor>
					</control>
					<control type="image">
						<top>49</top>
						<height>4</height>
						<texture border="0,0,220,0" colordiffuse="$VAR[PanelListSeparatorColorVar]">panels/separator.png</texture>
					</control>
				</itemlayout>
				<focusedlayout height="49">
					<control type="image">
						<top>1</top>
						<left>181</left>
						<height>48</height>
						<texture border="10" colordiffuse="$VAR[PanelHighlightColorVar]">buttons/list-select-focus.png</texture>
					</control>
					<control type="label">
						<width>180</width>
						<font>Font28_Reg</font>
						<label>$INFO[ListItem.Label2]</label>
						<textcolor>$VAR[PanelTextColorVar]</textcolor>
					</control>
					<control type="image">
						<top>1</top>
						<left>180</left>
						<width>4</width>
						<height>48</height>
						<texture colordiffuse="$VAR[PanelListSeparatorColorVar]">panels/line-vertical.png</texture>
					</control>
					<control type="label">
						<left>200</left>
						<font>Font28_Reg</font>
						<label>$INFO[ListItem.Label]</label>
						<textcolor>$VAR[PanelFocusTextColorVar]</textcolor>
					</control>
					<control type="image">
						<top>49</top>
						<height>4</height>
						<texture border="0,0,220,0" colordiffuse="$VAR[PanelListSeparatorColorVar]">panels/separator.png</texture>
					</control>
				</focusedlayout>
				<content sortby="year" sortorder="ascending">musicdb://albums/$INFO[ListItem.DBID]</content>
			</control>
		</definition>
	</include>
	<include name="DialogInfoExtenedInfo">
		<param name="id"></param>
		<param name="content"></param>
		<param name="visible">true</param>
		<definition>
			<control type="group">
				<visible>Control.HasFocus(9$PARAM[id]) | Control.HasFocus($PARAM[id])</visible>
				<visible>$PARAM[visible]</visible>
				<include>AnimationVisibleFade</include>
				<control type="panel" id="9$PARAM[id]">
					<orientation>horizontal</orientation>
					<ondown>9000</ondown>
					<itemlayout height="322" width="234">
						<control type="image">
							<width>224</width>
							<texture border="10" colordiffuse="$VAR[PanelSubTextColorVar]">buttons/panel-select-focus.png</texture>
						</control>
						<control type="image">
							<top>10</top>
							<left>10</left>
							<width>204</width>
							<height>302</height>
							<aspectratio>scale</aspectratio>
							<texture>$INFO[ListItem.Art(thumb)]</texture>
						</control>
					</itemlayout>
					<focusedlayout height="322" width="234">
						<control type="image">
							<width>224</width>
							<texture border="10" colordiffuse="$VAR[PanelHighlightColorVar]">buttons/panel-select-focus.png</texture>
						</control>
						<control type="image">
							<top>10</top>
							<left>10</left>
							<width>204</width>
							<height>302</height>
							<aspectratio>scale</aspectratio>
							<texture>$INFO[ListItem.Art(thumb)]</texture>
						</control>
					</focusedlayout>
					<content>$PARAM[content]</content>
				</control>
				<control type="image">
					<top>275</top>
					<height>58</height>
					<texture border="30" colordiffuse="$VAR[PanelListSeparatorColorVar]">buttons/list-select-nofocus.png</texture>
				</control>
			</control>
		</definition>
	</include>
	<include name="DialogInfoExtenedInfoYoutube">
		<param name="id"></param>
		<param name="content"></param>
		<definition>
			<control type="group">
				<visible>Control.HasFocus(9$PARAM[id]) | Control.HasFocus($PARAM[id])</visible>
				<include>AnimationVisibleFade</include>
				<control type="panel" id="9$PARAM[id]">
					<orientation>horizontal</orientation>
					<ondown>9000</ondown>
					<itemlayout height="284" width="390">
						<control type="image">
							<width>380</width>
							<texture border="10" colordiffuse="$VAR[PanelSubTextColorVar]">buttons/panel-select-focus.png</texture>
						</control>
						<control type="image">
							<top>10</top>
							<left>10</left>
							<width>360</width>
							<height>264</height>
							<aspectratio>scale</aspectratio>
							<texture>$INFO[ListItem.Art(thumb)]</texture>
						</control>
					</itemlayout>
					<focusedlayout height="284" width="390">
						<control type="image">
							<width>380</width>
							<texture border="10" colordiffuse="$VAR[PanelHighlightColorVar]">buttons/panel-select-focus.png</texture>
						</control>
						<control type="image">
							<top>10</top>
							<left>10</left>
							<width>360</width>
							<height>264</height>
							<aspectratio>scale</aspectratio>
							<texture>$INFO[ListItem.Art(thumb)]</texture>
						</control>
					</focusedlayout>
					<content>$PARAM[content]</content>
				</control>
				<control type="label">
					<visible>!Control.HasFocus(9$PARAM[id])</visible>
					<top>283</top>
					<height>49</height>
					<font>Font28_Reg</font>
					<label>$INFO[Container(9$PARAM[id]).ListItem.Label]</label>
					<textcolor>$VAR[PanelSubTextColorVar]</textcolor>
				</control>
				<control type="label">
					<visible>Control.HasFocus(9$PARAM[id])</visible>
					<top>283</top>
					<height>49</height>
					<font>Font28_Reg</font>
					<label>$INFO[Container(9$PARAM[id]).ListItem.Label]</label>
					<textcolor>$VAR[PanelTextColorVar]</textcolor>
				</control>
				<control type="image">
					<top>275</top>
					<height>58</height>
					<texture border="30" colordiffuse="$VAR[PanelListSeparatorColorVar]">buttons/list-select-nofocus.png</texture>
				</control>
			</control>
		</definition>
	</include>
	<include name="DialogInfoExtenedInfoMusic">
		<param name="id"></param>
		<param name="content"></param>
		<definition>
			<control type="group">
				<visible>![Control.HasFocus(101) | Control.HasFocus(112) | Control.HasFocus(113)] | Control.HasFocus($PARAM[id])</visible>
				<include>AnimationVisibleFade</include>
				<control type="panel" id="9$PARAM[id]">
					<orientation>horizontal</orientation>
					<ondown>9000</ondown>
					<itemlayout height="284" width="293">
						<control type="image">
							<width>280</width>
							<texture border="10" colordiffuse="$VAR[PanelSubTextColorVar]">buttons/panel-select-focus.png</texture>
						</control>
						<control type="image">
							<top>10</top>
							<left>10</left>
							<width>260</width>
							<height>264</height>
							<aspectratio>scale</aspectratio>
							<texture>$INFO[ListItem.Art(thumb)]</texture>
						</control>
					</itemlayout>
					<focusedlayout height="284" width="283">
						<control type="image">
							<width>280</width>
							<texture border="10" colordiffuse="$VAR[PanelHighlightColorVar]">buttons/panel-select-focus.png</texture>
						</control>
						<control type="image">
							<top>10</top>
							<left>10</left>
							<width>260</width>
							<height>264</height>
							<aspectratio>scale</aspectratio>
							<texture>$INFO[ListItem.Art(thumb)]</texture>
						</control>
					</focusedlayout>
					<content>$PARAM[content]</content>
				</control>
				<control type="label">
					<visible>!Control.HasFocus(9$PARAM[id])</visible>
					<top>283</top>
					<height>49</height>
					<font>Font28_Reg</font>
					<label>$INFO[Container(9$PARAM[id]).ListItem.Label]</label>
					<textcolor>$VAR[PanelSubTextColorVar]</textcolor>
				</control>
				<control type="label">
					<visible>Control.HasFocus(9$PARAM[id])</visible>
					<top>283</top>
					<height>49</height>
					<font>Font28_Reg</font>
					<label>$INFO[Container(9$PARAM[id]).ListItem.Label]</label>
					<textcolor>$VAR[PanelTextColorVar]</textcolor>
				</control>
				<control type="image">
					<top>275</top>
					<height>58</height>
					<texture border="30" colordiffuse="$VAR[PanelListSeparatorColorVar]">buttons/list-select-nofocus.png</texture>
				</control>
			</control>
		</definition>
	</include>
	<include name="DialogAddonInfo">
		<param name="infovisible">true</param>
		<param name="label"></param>
		<param name="label2"></param>
		<param name="textbox"></param>
		<param name="infocontent"></param>
		<definition>
			<include>DialogBackgroundFade</include>
			<centertop>50%</centertop>
			<centerleft>50%</centerleft>
			<width>1346</width>
			<height>752</height>
			<control type="image">
				<texture colordiffuse="$VAR[PanelShadowColorVar]" border="50">$VAR[DialogShadowVar]</texture>
			</control>
			<control type="image">
				<texture colordiffuse="$VAR[PanelStyleColorVar]" border="40">$VAR[DialogStyleVar]</texture>
			</control>
			<control type="image">
				<visible>!Skin.HasSetting(DialogSquare.texture)</visible>
				<top>20</top>
				<left>20</left>
				<right>20</right>
				<bottom>20</bottom>
				<aspectratio scalediffuse="false">scale</aspectratio>
				<texture diffuse="$PARAM[diffusetexture]" colordiffuse="$VAR[PanelTextureColorVar]">$INFO[Skin.String(PanelTexture.texture)]</texture>
			</control>
			<control type="image">
				<visible>Skin.HasSetting(DialogSquare.texture)</visible>
				<top>20</top>
				<left>20</left>
				<right>20</right>
				<bottom>20</bottom>
				<aspectratio scalediffuse="false">scale</aspectratio>
				<texture colordiffuse="$VAR[PanelTextureColorVar]">$INFO[Skin.String(PanelTexture.texture)]</texture>
			</control>
			<control type="image">
				<texture colordiffuse="$VAR[PanelEmbossColorVar]" border="40">$VAR[DialogEmbossVar]</texture>
			</control>
			<control type="label">
				<top>27</top>
				<left>50</left>
				<right>60</right>
				<height>70</height>
				<font>Font36_Bold_Caps</font>
				<label>$PARAM[label]</label>
				<textcolor>$VAR[PanelTextColorVar]</textcolor>
			</control>
			<control type="label">
				<top>68</top>
				<left>50</left>
				<right>60</right>
				<height>70</height>
				<font>Font32_Reg</font>
				<label>$PARAM[label2]</label>
				<textcolor>$VAR[PanelHighlightColorVar]</textcolor>
			</control>
			<control type="image">
				<top>136</top>
				<left>50</left>
				<right>50</right>
				<height>4</height>
				<texture border="1" colordiffuse="$VAR[PanelListSeparatorColorVar]">panels/separator.png</texture>
			</control>
			<control type="panel" id="9003">
				<visible>$PARAM[infovisible]</visible>
				<include>AnimationVisibleFade</include>
				<top>136</top>
				<left>50</left>
				<right>50</right>
				<height>246</height>
				<ondown>9000</ondown>
				<orientation>horizontal</orientation>
				<itemlayout height="49">
					<control type="label">
						<width>180</width>
						<font>Font28_Reg</font>
						<label>$INFO[ListItem.Label2]</label>
						<textcolor>$VAR[PanelTextColorVar]</textcolor>
					</control>
					<control type="image">
						<top>1</top>
						<left>200</left>
						<width>4</width>
						<height>48</height>
						<texture colordiffuse="$VAR[PanelListSeparatorColorVar]">panels/line-vertical-white.png</texture>
					</control>
					<control type="label">
						<left>220</left>
						<width>605</width>
						<font>Font28_Reg</font>
						<label>$INFO[ListItem.Label]</label>
						<textcolor>$VAR[PanelSubTextColorVar]</textcolor>
					</control>
					<control type="image">
						<top>49</top>
						<height>4</height>
						<texture border="0,0,220,0" colordiffuse="$VAR[PanelListSeparatorColorVar]">panels/separator.png</texture>
					</control>
				</itemlayout>
				<focusedlayout height="49">
					<control type="label">
						<width>180</width>
						<font>Font28_Reg</font>
						<label>$INFO[ListItem.Label2]</label>
						<textcolor>$VAR[PanelTextColorVar]</textcolor>
					</control>
					<control type="image">
						<top>1</top>
						<left>200</left>
						<width>4</width>
						<height>48</height>
						<texture colordiffuse="$VAR[PanelListSeparatorColorVar]">panels/line-vertical-white.png</texture>
					</control>
					<control type="label">
						<left>220</left>
						<width>605</width>
						<font>Font28_Reg</font>
						<label>$INFO[ListItem.Label]</label>
						<textcolor>$VAR[PanelSubTextColorVar]</textcolor>
					</control>
					<control type="image">
						<top>49</top>
						<height>4</height>
						<texture border="0,0,220,0" colordiffuse="$VAR[PanelListSeparatorColorVar]">panels/separator.png</texture>
					</control>
				</focusedlayout>
				<include>$PARAM[infocontent]</include>
			</control>
			<control type="group">
				<top>472</top>
				<left>40</left>
				<width>240</width>
				<height>240</height>
				<control type="image">
					<bordersize>10</bordersize>
					<fadetime>TextureFadeTime</fadetime>
					<aspectratio align="center" aligny="center">keep</aspectratio>
					<texture diffuse="diffuse/rounded5-220x220.png" fallback="DefaultTVShows.png">$INFO[ListItem.Icon]</texture>
				</control>
				<control type="image">
					<texture border="20">thumbs/overlay.png</texture>
				</control>
			</control>
			<control type="textbox">
				<top>482</top>
				<left>285</left>
				<right>50</right>
				<height>220</height>
				<font>Font30_Reg_105</font>
				<include>AutoScrollPlot</include>
				<label>$PARAM[textbox]</label>
				<textcolor>$VAR[PanelSubTextColorVar]</textcolor>
			</control>
		</definition>
	</include>
	<include name="PVRInfoContent">
		<content>
			<item>
				<label>$INFO[ListItem.ChannelName]</label>
				<label2>$LOCALIZE[19029]</label2>
				<visible>!String.IsEmpty(ListItem.ChannelName)</visible>
			</item>
			<item>
				<label>$INFO[ListItem.StartDate]</label>
				<label2>$LOCALIZE[552]</label2>
				<visible>!String.IsEmpty(ListItem.StartDate)</visible>
			</item>
			<item>
				<label>$INFO[ListItem.StartTime]$INFO[ListItem.EndTime, - ]</label>
				<label2>$LOCALIZE[555]</label2>
				<visible>!String.IsEmpty(ListItem.StartTime)</visible>
			</item>
			<item>
				<label>$INFO[ListItem.Duration]</label>
				<label2>$LOCALIZE[180]</label2>
				<visible>!String.IsEmpty(ListItem.Duration)</visible>
			</item>
			<item>
				<label>$INFO[PVR.BackendName]</label>
				<label2>$LOCALIZE[19210]</label2>
				<visible>!String.IsEmpty(PVR.BackendName)</visible>
			</item>
		</content>
	</include>
	<include name="AddonInfoContent">
		<content>
			<item>
				<label>$INFO[ListItem.AddonVersion]</label>
				<label2>$LOCALIZE[19114]</label2>
			</item>
			<item>
				<label>$INFO[ListItem.AddonCreator]</label>
				<label2>by</label2>
			</item>
			<item>
				<label>$INFO[ListItem.Property(Addon.ID)]</label>
				<label2>$LOCALIZE[560]</label2>
			</item>
			<item>
				<label>$INFO[ListItem.AddonType]</label>
				<label2>$LOCALIZE[467]</label2>
			</item>
			<item>
				<label>$INFO[ListItem.AddonOrigin]</label>
				<label2>$LOCALIZE[31303]</label2>
			</item>
		</content>
	</include>

	<variable name="TMDBInfoID">
		<value condition="Container.Content(movies) + !String.IsEmpty(ListItem.Property(imdb_id))">imdb_id=$INFO[ListItem.Property(imdb_id)]</value>
		<value condition="Container.Content(movies) + !String.IsEmpty(ListItem.IMDBNumber) + !String.StartsWith(ListItem.IMDBNumber,xx)">imdb_id=$INFO[ListItem.IMDBNumber]</value>
		<value condition="[Container.Content(tvshows) | Container.Content(seasons) | Container.Content(episodes)] + !String.IsEmpty(ListItem.TvShowTitle)">query=$INFO[ListItem.TvShowTitle]</value>
		<value condition="!String.IsEmpty(ListItem.Title) + !String.IsEmpty(ListItem.Year)">query=$INFO[ListItem.Title]&amp;year=$INFO[ListItem.Year]</value>
		<value condition="!String.IsEmpty(ListItem.Title)">query=$INFO[ListItem.Title]</value>
		<value>query=$INFO[ListItem.Label]</value>
	</variable>
	<variable name="TMDBInfoType">
		<value condition="Container.Content(movies) | Container.Content(set)">type=movie</value>
		<value condition="Container.Content(tvshows) | Container.Content(seasons) | Container.Content(episode)">type=tv</value>
	</variable>
	<variable name="VideoInfoContainerIcon">
		<value condition="Control.HasFocus(114)">$VAR[IconPathVar]movies.png</value>
		<value>$VAR[IconPathVar]person.png</value>
	</variable>
	<variable name="VideoInfoContainerLabel">
		<value condition="Control.HasFocus(111)">Cast</value>
		<value condition="Control.HasFocus(112)">Cast</value>
		<value condition="Control.HasFocus(113)">Crew</value>
		<value condition="Control.HasFocus(114)">$INFO[ListItem.Set]</value>
		<value condition="Control.HasFocus(115)">Movies by director$INFO[ListItem.Director, ,]</value>
		<value condition="Control.HasFocus(116)">$INFO[Container(506).ListItem.DBTYPE,, ] by written by $INFO[ListItem.Writer, ,]</value>
	</variable>
	<variable name="VideoInfoContainerLabel2">
		<value condition="Control.HasFocus(501)">$INFO[Container(501).ListItem.Label][COLOR $VAR[PanelSubTextColorVar]]$INFO[Container(501).ListItem.Label2, as ][/COLOR]</value>
		<value condition="Control.HasFocus(502)">$INFO[Container(502).ListItem.Label][COLOR $VAR[PanelSubTextColorVar]]$INFO[Container(502).ListItem.Label2, as ][/COLOR]</value>
		<value condition="Control.HasFocus(503)">$INFO[Container(503).ListItem.Label2,, ][COLOR $VAR[PanelSubTextColorVar]]$INFO[Container(503).ListItem.Label][/COLOR]</value>
		<value condition="Control.HasFocus(504)">$INFO[Container(504).ListItem.Label,, ][COLOR $VAR[PanelSubTextColorVar]]$INFO[Container(504).ListItem.Year,(,)][/COLOR]</value>

	</variable>
	<variable name="VideoInfoSets">
		<value condition="Container.Content(movies) + !String.IsEmpty(ListItem.Set)">plugin://plugin.video.themoviedb.helper/?info=collection&amp;type=movie&amp;query=$INFO[ListItem.Set]</value>
		<value condition="Container.Content(movies)">$INFO[ListItem.SetID,videodb://movies/sets/,/]</value>
	</variable>
	<variable name="VideoInfoYouTube">
		<value condition="System.HasAddon(plugin.video.youtube) + Container.Content(movies)">$INFO[ListItem.Label,plugin://plugin.video.youtube/search/?q=,]</value>
	</variable>


	<include name="CastItem">
		<param name="id"></param>
		<definition>
			<item>
				<label>$INFO[Container(50).ListItem($PARAM[id]).Label]</label>
				<label2>$INFO[Container(50).ListItem($PARAM[id]).Label2]</label2>
				<icon>$INFO[Container(50).ListItem($PARAM[id]).Icon]</icon>
				<visible>!String.IsEmpty(Container(50).ListItem($PARAM[id]).Label)</visible>
			</item>
		</definition>
	</include>
	<include name="TMDBCastItem">
		<param name="id"></param>
		<definition>
			<item>
				<label>$INFO[Container(500).ListItemAbsolute(1).Property(Cast.$PARAM[id].Name)]</label>
				<label2>$INFO[Container(500).ListItemAbsolute(1).Property(Cast.$PARAM[id].Role)]</label2>
				<icon>$INFO[Container(500).ListItemAbsolute(1).Property(Cast.$PARAM[id].Thumb)]</icon>
				<visible>!String.IsEmpty(Container(500).ListItemAbsolute(1).Property(Cast.$PARAM[id].Name))</visible>
			</item>
		</definition>
	</include>
	<include name="TMDBCastListContent">
		<include content="TMDBCastItem">
			<param name="id">1</param>
		</include>
		<include content="TMDBCastItem">
			<param name="id">2</param>
		</include>
		<include content="TMDBCastItem">
			<param name="id">3</param>
		</include>
		<include content="TMDBCastItem">
			<param name="id">4</param>
		</include>
		<include content="TMDBCastItem">
			<param name="id">5</param>
		</include>
		<include content="TMDBCastItem">
			<param name="id">6</param>
		</include>
		<include content="TMDBCastItem">
			<param name="id">7</param>
		</include>
		<include content="TMDBCastItem">
			<param name="id">8</param>
		</include>
		<include content="TMDBCastItem">
			<param name="id">9</param>
		</include>
		<include content="TMDBCastItem">
			<param name="id">10</param>
		</include>
		<include content="TMDBCastItem">
			<param name="id">11</param>
		</include>
		<include content="TMDBCastItem">
			<param name="id">12</param>
		</include>
		<include content="TMDBCastItem">
			<param name="id">13</param>
		</include>
		<include content="TMDBCastItem">
			<param name="id">14</param>
		</include>
		<include content="TMDBCastItem">
			<param name="id">15</param>
		</include>
		<include content="TMDBCastItem">
			<param name="id">16</param>
		</include>
		<include content="TMDBCastItem">
			<param name="id">17</param>
		</include>
		<include content="TMDBCastItem">
			<param name="id">18</param>
		</include>
		<include content="TMDBCastItem">
			<param name="id">19</param>
		</include>
		<include content="TMDBCastItem">
			<param name="id">20</param>
		</include>
		<include content="TMDBCastItem">
			<param name="id">21</param>
		</include>
		<include content="TMDBCastItem">
			<param name="id">22</param>
		</include>
		<include content="TMDBCastItem">
			<param name="id">23</param>
		</include>
		<include content="TMDBCastItem">
			<param name="id">24</param>
		</include>
		<include content="TMDBCastItem">
			<param name="id">25</param>
		</include>
		<include content="TMDBCastItem">
			<param name="id">26</param>
		</include>
		<include content="TMDBCastItem">
			<param name="id">27</param>
		</include>
		<include content="TMDBCastItem">
			<param name="id">28</param>
		</include>
		<include content="TMDBCastItem">
			<param name="id">29</param>
		</include>
		<include content="TMDBCastItem">
			<param name="id">30</param>
		</include>
		<include content="TMDBCastItem">
			<param name="id">31</param>
		</include>
		<include content="TMDBCastItem">
			<param name="id">32</param>
		</include>
		<include content="TMDBCastItem">
			<param name="id">33</param>
		</include>
		<include content="TMDBCastItem">
			<param name="id">34</param>
		</include>
		<include content="TMDBCastItem">
			<param name="id">35</param>
		</include>
		<include content="TMDBCastItem">
			<param name="id">36</param>
		</include>
		<include content="TMDBCastItem">
			<param name="id">37</param>
		</include>
		<include content="TMDBCastItem">
			<param name="id">38</param>
		</include>
		<include content="TMDBCastItem">
			<param name="id">39</param>
		</include>
		<include content="TMDBCastItem">
			<param name="id">40</param>
		</include>
	</include>
	<include name="CastListContent">
		<include content="CastItem">
			<param name="id">0</param>
		</include>
		<include content="CastItem">
			<param name="id">1</param>
		</include>
		<include content="CastItem">
			<param name="id">2</param>
		</include>
		<include content="CastItem">
			<param name="id">3</param>
		</include>
		<include content="CastItem">
			<param name="id">4</param>
		</include>
		<include content="CastItem">
			<param name="id">5</param>
		</include>
		<include content="CastItem">
			<param name="id">6</param>
		</include>
		<include content="CastItem">
			<param name="id">7</param>
		</include>
		<include content="CastItem">
			<param name="id">8</param>
		</include>
		<include content="CastItem">
			<param name="id">9</param>
		</include>
		<include content="CastItem">
			<param name="id">10</param>
		</include>
		<include content="CastItem">
			<param name="id">11</param>
		</include>
		<include content="CastItem">
			<param name="id">12</param>
		</include>
		<include content="CastItem">
			<param name="id">13</param>
		</include>
		<include content="CastItem">
			<param name="id">14</param>
		</include>
		<include content="CastItem">
			<param name="id">15</param>
		</include>
		<include content="CastItem">
			<param name="id">16</param>
		</include>
		<include content="CastItem">
			<param name="id">17</param>
		</include>
		<include content="CastItem">
			<param name="id">18</param>
		</include>
		<include content="CastItem">
			<param name="id">19</param>
		</include>
		<include content="CastItem">
			<param name="id">20</param>
		</include>
		<include content="CastItem">
			<param name="id">21</param>
		</include>
		<include content="CastItem">
			<param name="id">22</param>
		</include>
		<include content="CastItem">
			<param name="id">23</param>
		</include>
		<include content="CastItem">
			<param name="id">24</param>
		</include>
		<include content="CastItem">
			<param name="id">25</param>
		</include>
		<include content="CastItem">
			<param name="id">26</param>
		</include>
		<include content="CastItem">
			<param name="id">27</param>
		</include>
		<include content="CastItem">
			<param name="id">28</param>
		</include>
		<include content="CastItem">
			<param name="id">29</param>
		</include>
		<include content="CastItem">
			<param name="id">30</param>
		</include>
		<include content="CastItem">
			<param name="id">31</param>
		</include>
		<include content="CastItem">
			<param name="id">32</param>
		</include>
		<include content="CastItem">
			<param name="id">33</param>
		</include>
		<include content="CastItem">
			<param name="id">34</param>
		</include>
		<include content="CastItem">
			<param name="id">35</param>
		</include>
		<include content="CastItem">
			<param name="id">36</param>
		</include>
		<include content="CastItem">
			<param name="id">37</param>
		</include>
		<include content="CastItem">
			<param name="id">38</param>
		</include>
		<include content="CastItem">
			<param name="id">39</param>
		</include>
		<include content="TMDBCastItem">
			<param name="id">40</param>
		</include>
	</include>
</includes>