<settings>
	<!-- System Poster -->
	<setting id="SystemBackgroundPoster" value="" label="$LOCALIZE[231]"/>
	<setting id="SystemBackgroundPoster" value="MoviesRecentlyAdded" label="$LOCALIZE[20386]"/>
	<setting id="SystemBackgroundPoster" value="MoviesRecentlyReleased" label="$LOCALIZE[31101]"/>
	<setting id="SystemBackgroundPoster" value="MoviesRecommended" label="$LOCALIZE[31102]"/>
	<setting id="SystemBackgroundPoster" value="MoviesRandom" label="$LOCALIZE[31103]"/>
	<setting id="SystemBackgroundPoster" value="MoviesSets" label="$LOCALIZE[31104]"/>
	<setting id="SystemBackgroundPoster" value="MoviesTop250" label="$LOCALIZE[31105]"/>
	<setting id="SystemBackgroundPoster" value="MoviesTop250Random" label="$LOCALIZE[31106]"/>
	<setting id="SystemBackgroundPoster" value="MoviesInCinema" label="$LOCALIZE[31107]"/>
	<setting id="SystemBackgroundPoster" value="MoviesUpComing" label="$LOCALIZE[31108]"/>
	<setting id="SystemBackgroundPoster" value="MoviesPopular" label="$LOCALIZE[31109]"/>
	<setting id="SystemBackgroundPoster" value="MoviesTopRated" label="$LOCALIZE[31110]"/>
	<setting id="SystemBackgroundPoster" value="TVShowsRecentlyAdded" label="$LOCALIZE[31111]"/>
	<setting id="SystemBackgroundPoster" value="TVShowsRecentlyReleased" label="$LOCALIZE[31112]"/>
	<setting id="SystemBackgroundPoster" value="TVShowsRecommended" label="$LOCALIZE[31113]"/>
	<setting id="SystemBackgroundPoster" value="TVShowsRandom" label="$LOCALIZE[31114]"/>
	<setting id="SystemBackgroundPoster" value="TVShowsNextAired" label="$LOCALIZE[31115]"/>
	<setting id="SystemBackgroundPoster" value="TVShowsPopular" label="$LOCALIZE[31116]"/>
	<setting id="SystemBackgroundPoster" value="TVShowsTopRated" label="$LOCALIZE[31117]"/>
	<setting id="SystemBackgroundPoster" value="TVShowsOnAir" label="$LOCALIZE[31118]"/>
	<setting id="SystemBackgroundPoster" value="TVShowsAiringToday" label="$LOCALIZE[31119]"/>
	<setting id="SystemBackgroundPoster" value="MusicVideosRecentlyAdded.Square" label="$LOCALIZE[20390]"/>
	<setting id="SystemBackgroundPoster" value="MusicVideosRecentlyReleased.Square" label="$LOCALIZE[31120]"/>
	<setting id="SystemBackgroundPoster" value="MusicVideosMostWatched.Square" label="$LOCALIZE[31121]"/>
	<setting id="SystemBackgroundPoster" value="MusicVideosRandom.Square" label="$LOCALIZE[31122]"/>
	<setting id="SystemBackgroundPoster" value="ArtistsRandom.Square" label="$LOCALIZE[31123]"/>
	<setting id="SystemBackgroundPoster" value="AlbumsRecentlyAdded.Square" label="$LOCALIZE[359]"/>
	<setting id="SystemBackgroundPoster" value="AlbumsRecentlyReleased.Square" label="$LOCALIZE[31124]"/>
	<setting id="SystemBackgroundPoster" value="AlbumsMostPlayed.Square" label="$LOCALIZE[31125]"/>
	<setting id="SystemBackgroundPoster" value="AlbumsRandom.Square" label="$LOCALIZE[31126]"/>
	<setting id="SystemBackgroundPoster" value="PVRChannels.Square" label="$LOCALIZE[31127]"/>
	<!-- System Case -->
	<setting id="SystemBackgroundPosterCase" value="" label="$LOCALIZE[231]"/>
	<setting id="SystemBackgroundPosterCase" value="Case" label="Case"/>
	<setting id="SystemBackgroundPosterCase" value="ClearCase" label="Clear Case"/>
	<setting id="SystemBackgroundPosterCase" value="Glass" label="Glass"/>
	





	<!-- Settings Fanart Overlay  -->
	<setting id="SystemBackgroundOverlay" value="" label="$LOCALIZE[571]"/>
	<setting id="SystemBackgroundOverlay" value="colors/black.png" label="Dark"/>
	<setting id="SystemBackgroundOverlay" value="colors/white.png" label="Light"/>
	<setting id="SystemBackgroundOverlay" value="none" label="$LOCALIZE[231]"/>
	
	<!-- Weather Fanart -->
	<setting id="WeatherBackground" value="" label="$LOCALIZE[571]"/>
	<setting id="WeatherBackground" value="Single" label="$LOCALIZE[31007]">
		<onselect condition="True">RunScript(script.skin.helper.service,action=selectimage,skinstring=SystemBackgroundFallback,resourceaddon=resource.images.skinbackgrounds)</onselect>
	</setting>
	<setting id="WeatherBackground" value="Multi" label="$LOCALIZE[31008]">
		<onselect condition="True">RunScript(script.skin.helper.service,action=setresourceaddon,skinstring=SystemBackgroundFallback,addontype=resource.images.skinbackgrounds)</onselect>
	</setting>
	<setting id="WeatherBackground" value="SkinHelper" label="Library backgrounds">
		<onselect condition="True">RunScript(script.skin.helper.service,action=selectimage,skinstring=SystemBackgroundFallback,skinhelperbackgrounds=true)</onselect>
	</setting>
	<setting id="WeatherBackground" value="None" label="$LOCALIZE[231]"/>
	<!-- Settings Fanart Overlay  -->
	<setting id="WeatherBackgroundOverlay" value="" label="$LOCALIZE[571]"/>
	<setting id="WeatherBackgroundOverlay" value="colors/black.png" label="Dark"/>
	<setting id="WeatherBackgroundOverlay" value="colors/white.png" label="Light"/>
	<setting id="WeatherBackgroundOverlay" value="None" label="$LOCALIZE[231]"/>





	<!-- Settings Color -->
	<setting id="SettingsColor" value="" label="$LOCALIZE[31049]" description="[COLOR $VAR[SystemHighlightColorVar]]$VAR[SystemHighlightColorLabelVar][/COLOR]">
		<onselect condition="True">RunScript(script.skin.helper.colorpicker,skinstring=SystemHighlight.color,header=$LOCALIZE[31049])</onselect>
	</setting>
	<setting id="SettingsColor" value="" label="$LOCALIZE[31056]" description="[COLOR $VAR[SystemPanelColorVar]]$VAR[SystemPanelColorLabelVar][/COLOR]">
		<onselect condition="True">RunScript(script.skin.helper.colorpicker,skinstring=SystemPanel.color,header=$LOCALIZE[31056])</onselect>
	</setting>
	<setting id="SettingsColor" value="" label="$LOCALIZE[31048]" description="[COLOR $VAR[SystemGlowColorVar]]$VAR[SystemGlowColorLabelVar][/COLOR]">
		<onselect condition="True">RunScript(script.skin.helper.colorpicker,skinstring=SystemGlow.color,header=$LOCALIZE[31048])</onselect>
	</setting>
	<setting id="SettingsColor" value="" label="$LOCALIZE[31042]" description="[COLOR $VAR[SystemTopbarColorVar]]$VAR[SystemTopbarColorLabelVar][/COLOR]">
		<onselect condition="True">RunScript(script.skin.helper.colorpicker,skinstring=SystemTopbar.color,header=$LOCALIZE[31042])</onselect>
	</setting>
	<setting id="SettingsColor" value="" label="$LOCALIZE[31047]" description="[COLOR $VAR[SystemFloorColorVar]]$VAR[SystemFloorColorLabelVar][/COLOR]">
		<onselect condition="True">RunScript(script.skin.helper.colorpicker,skinstring=SystemFloor.color,header=$LOCALIZE[31047])</onselect>
	</setting>
	<setting id="SettingsColor" value="" label="$LOCALIZE[33068]" description="[COLOR $VAR[SystemBackgroundColorVar]]$VAR[SystemBackgroundColorLabelVar][/COLOR]">
		<onselect condition="True">RunScript(script.skin.helper.colorpicker,skinstring=SystemBackground.color,header=$LOCALIZE[33068])</onselect>
	</setting>			






	
</settings>